python_secrets_manager/__init__.py
python_secrets_manager/root.py
python_secrets_manager/utils.py
python_secrets_manager-0.1.1.dist-info/WHEEL
python_secrets_manager-0.1.1.dist-info/METADATA
python_secrets_manager-0.1.1.dist-info/RECORD
